{
  "total_with_analysis_date": 83689,
  "avg_days_to_analysis": 2037.5,
  "p90_days_to_analysis": 8016,
  "awaiting_analysis_count": 3483,
  "undergoing_analysis_count": 666,
  "deferred_count": 29363,
  "status_breakdown": {
    "Modified": 33527,
    "Analyzed": 50162,
    "Deferred": 29363,
    "Rejected": 3339,
    "Unknown": 17176,
    "Awaiting Analysis": 3483,
    "Undergoing Analysis": 666,
    "Received": 242
  },
  "distribution_buckets": [
    {
      "range": "0\u20137 days",
      "count": 19156
    },
    {
      "range": "8\u201330 days",
      "count": 10876
    },
    {
      "range": "31\u201390 days",
      "count": 6290
    },
    {
      "range": "91\u2013180 days",
      "count": 9422
    },
    {
      "range": "181\u2013365 days",
      "count": 11149
    },
    {
      "range": ">365 days",
      "count": 26796
    }
  ],
  "generated_at": "2026-04-18T03:18:41Z"
}