{
  "comparable_conflicts": 1698,
  "vector_only_conflicts": 67,
  "generated_at": "2026-04-25T06:36:11Z",
  "metrics": [
    {
      "key": "A",
      "name": "Availability",
      "total": 1698,
      "disagree_count": 522,
      "disagree_rate": 30.7,
      "nvd_higher_count": 311,
      "gh_higher_count": 211,
      "top_transitions": [
        {
          "transition": "H\u2192L",
          "count": 171
        },
        {
          "transition": "N\u2192L",
          "count": 122
        },
        {
          "transition": "H\u2192N",
          "count": 112
        },
        {
          "transition": "N\u2192H",
          "count": 77
        },
        {
          "transition": "L\u2192N",
          "count": 28
        }
      ]
    },
    {
      "key": "C",
      "name": "Confidentiality",
      "total": 1698,
      "disagree_count": 491,
      "disagree_rate": 28.9,
      "nvd_higher_count": 245,
      "gh_higher_count": 246,
      "top_transitions": [
        {
          "transition": "H\u2192L",
          "count": 156
        },
        {
          "transition": "L\u2192H",
          "count": 150
        },
        {
          "transition": "N\u2192L",
          "count": 57
        },
        {
          "transition": "H\u2192N",
          "count": 55
        },
        {
          "transition": "N\u2192H",
          "count": 39
        }
      ]
    },
    {
      "key": "S",
      "name": "Scope",
      "total": 1698,
      "disagree_count": 469,
      "disagree_rate": 27.6,
      "nvd_higher_count": 182,
      "gh_higher_count": 287,
      "top_transitions": [
        {
          "transition": "U\u2192C",
          "count": 287
        },
        {
          "transition": "C\u2192U",
          "count": 182
        }
      ]
    },
    {
      "key": "I",
      "name": "Integrity",
      "total": 1698,
      "disagree_count": 460,
      "disagree_rate": 27.1,
      "nvd_higher_count": 259,
      "gh_higher_count": 201,
      "top_transitions": [
        {
          "transition": "H\u2192L",
          "count": 128
        },
        {
          "transition": "L\u2192H",
          "count": 119
        },
        {
          "transition": "L\u2192N",
          "count": 69
        },
        {
          "transition": "H\u2192N",
          "count": 62
        },
        {
          "transition": "N\u2192L",
          "count": 45
        }
      ]
    },
    {
      "key": "AC",
      "name": "Attack Complexity",
      "total": 1698,
      "disagree_count": 452,
      "disagree_rate": 26.6,
      "nvd_higher_count": 416,
      "gh_higher_count": 36,
      "top_transitions": [
        {
          "transition": "L\u2192H",
          "count": 416
        },
        {
          "transition": "H\u2192L",
          "count": 36
        }
      ]
    },
    {
      "key": "PR",
      "name": "Privileges Required",
      "total": 1698,
      "disagree_count": 420,
      "disagree_rate": 24.7,
      "nvd_higher_count": 286,
      "gh_higher_count": 134,
      "top_transitions": [
        {
          "transition": "N\u2192L",
          "count": 157
        },
        {
          "transition": "L\u2192N",
          "count": 101
        },
        {
          "transition": "L\u2192H",
          "count": 94
        },
        {
          "transition": "N\u2192H",
          "count": 35
        },
        {
          "transition": "H\u2192N",
          "count": 20
        }
      ]
    },
    {
      "key": "UI",
      "name": "User Interaction",
      "total": 1698,
      "disagree_count": 244,
      "disagree_rate": 14.4,
      "nvd_higher_count": 126,
      "gh_higher_count": 118,
      "top_transitions": [
        {
          "transition": "N\u2192R",
          "count": 126
        },
        {
          "transition": "R\u2192N",
          "count": 118
        }
      ]
    },
    {
      "key": "AV",
      "name": "Attack Vector",
      "total": 1698,
      "disagree_count": 110,
      "disagree_rate": 6.5,
      "nvd_higher_count": 90,
      "gh_higher_count": 20,
      "top_transitions": [
        {
          "transition": "N\u2192L",
          "count": 72
        },
        {
          "transition": "L\u2192N",
          "count": 16
        },
        {
          "transition": "N\u2192A",
          "count": 14
        },
        {
          "transition": "A\u2192N",
          "count": 4
        },
        {
          "transition": "A\u2192L",
          "count": 2
        }
      ]
    }
  ]
}